coinswitch_client/APIClient.py
coinswitch_client/TransactionManager.py
coinswitch_client/__init__.py
coinswitchclient-0.0.2.dist-info/LICENSE.txt
coinswitchclient-0.0.2.dist-info/METADATA
coinswitchclient-0.0.2.dist-info/WHEEL
coinswitchclient-0.0.2.dist-info/top_level.txt
coinswitchclient-0.0.2.dist-info/RECORD
