Metadata-Version: 2.1
Name: coinswitchclient
Version: 0.0.2
Summary: A simple coinswitch (v1,v2) client api
Home-page: https://github.com/Willena/PythonCoinSwitchClient
Author: Guillaume VILLENA
Author-email: contact@guillaumevillena.fr
License: UNKNOWN
Project-URL: Bug Reports, https://github.com/Willena/PythonCoinSwitchClient/issues
Project-URL: Funding, https://paypal.me/GuillaumeVillena
Project-URL: Say Thanks!, https://paypal.me/GuillaumeVillena
Project-URL: Source, https://github.com/Willena/PythonCoinSwitchClient
Keywords: api lib library coinswicth client cryptos
Platform: UNKNOWN
Classifier: Development Status :: 4 - Beta
Classifier: Intended Audience :: Developers
Classifier: Topic :: Software Development :: Build Tools
Classifier: License :: OSI Approved :: MIT License
Classifier: Programming Language :: Python :: 2
Classifier: Programming Language :: Python :: 2.7
Classifier: Programming Language :: Python :: 3
Classifier: Programming Language :: Python :: 3.4
Classifier: Programming Language :: Python :: 3.5
Classifier: Programming Language :: Python :: 3.6
Classifier: Programming Language :: Python :: 3.7
Requires-Dist: requests
